OrfPP/OrfPP.py
OrfPP/__init__.py
OrfPP/funcs.py
OrfPP/getOpts.py
OrfPP-1.0.dist-info/LICENSE
OrfPP-1.0.dist-info/METADATA
OrfPP-1.0.dist-info/WHEEL
OrfPP-1.0.dist-info/entry_points.txt
OrfPP-1.0.dist-info/top_level.txt
OrfPP-1.0.dist-info/RECORD
