Metadata-Version: 2.1
Name: OrfPP
Version: 1.0
Summary: An ORF predictor from SNPs
Home-page: https://github.com/songbo446
Author: Bo Song
Author-email: songbo446@yeah.net
License: UNKNOWN
Platform: UNKNOWN
Classifier: Programming Language :: Python :: 3
Classifier: License :: OSI Approved :: MIT License
Classifier: Operating System :: OS Independent
License-File: LICENSE
